pydelt/__init__.py
pydelt/autodiff.py
pydelt/derivatives.py
pydelt/integrals.py
pydelt/interpolation.py
pydelt/multivariate.py
pydelt/stochastic.py
pydelt/stochastic_helpers.py
pydelt/tensor_derivatives.py
pydelt/tests/test_autodiff.py
pydelt/tests/test_autodiff_multivariate.py
pydelt/tests/test_derivatives.py
pydelt/tests/test_derivatives_multivariate.py
pydelt/tests/test_integrals.py
pydelt/tests/test_integrals_multivariate.py
pydelt/tests/test_interpolation_advanced.py
pydelt/tests/test_interpolation_multivariate.py
pydelt/tests/test_multivariate.py
pydelt/tests/test_stochastic_derivatives.py
pydelt/tests/test_universal_differentiation.py
pydelt/tests/test_window_functions.py
pydelt-0.8.0.dist-info/METADATA
pydelt-0.8.0.dist-info/WHEEL
pydelt-0.8.0.dist-info/licenses/LICENSE
pydelt-0.8.0.dist-info/RECORD
