Metadata-Version: 2.4
Name: pydelt
Version: 0.8.0
Summary: Advanced numerical function interpolation and differentiation with universal API, multivariate calculus, window functions, and stochastic extensions
Project-URL: Homepage, https://github.com/MikeHLee/pydelt
Project-URL: Documentation, https://pydelt.readthedocs.io/
Project-URL: Repository, https://github.com/MikeHLee/pydelt.git
Project-URL: Issues, https://github.com/MikeHLee/pydelt/issues
Project-URL: Changelog, https://github.com/MikeHLee/pydelt/blob/main/CHANGELOG.md
Author-email: Michael Harrison Lee <leemichael289@gmail.com>
License-File: LICENSE
Keywords: automatic-differentiation,derivatives,financial-modeling,gradient,hessian,interpolation,ito-lemma,jacobian,machine-learning,multivariate-calculus,numerical-differentiation,stochastic-calculus,stratonovich
Classifier: Development Status :: 4 - Beta
Classifier: Intended Audience :: Science/Research
Classifier: License :: OSI Approved :: MIT License
Classifier: Operating System :: OS Independent
Classifier: Programming Language :: Python :: 3
Classifier: Programming Language :: Python :: 3.8
Classifier: Programming Language :: Python :: 3.9
Classifier: Programming Language :: Python :: 3.10
Classifier: Programming Language :: Python :: 3.11
Classifier: Programming Language :: Python :: 3.12
Classifier: Topic :: Scientific/Engineering :: Mathematics
Classifier: Topic :: Software Development :: Libraries :: Python Modules
Requires-Python: >=3.8
Requires-Dist: numpy>=1.20.0
Requires-Dist: pandas>=1.3.0
Requires-Dist: plotly>=5.0.0
Requires-Dist: scipy>=1.7.0
Requires-Dist: statsmodels>=0.13.0
